{
  "lastUpdated": "2026-03-31T19:00:00Z",
  "systemStatus": {
    "weeklyVisitors": 0,
    "uniqueVisitors": 0,
    "topReferralSource": "Awaiting data",
    "emailSignups": 0,
    "collectClicks": 0,
    "salesCount": 0,
    "revenue": 0
  },
  "hotImages": [],
  "collectorPipeline": {
    "visitors": 0,
    "engaged": 0,
    "interested": 0,
    "collectors": 0
  },
  "trafficSources": [
    {
      "source": "Awaiting first Plausible report",
      "visitors": 0
    }
  ],
  "seriesPerformance": [
    {
      "series": "Texture & Dormancy",
      "views": 0,
      "avgTimeSeconds": 0,
      "collectClicks": 0,
      "conversationRate": 0
    },
    {
      "series": "Savannah 2026",
      "views": 0,
      "avgTimeSeconds": 0,
      "collectClicks": 0,
      "conversationRate": 0
    },
    {
      "series": "Intimacy",
      "views": 0,
      "avgTimeSeconds": 0,
      "collectClicks": 0,
      "conversationRate": 0
    },
    {
      "series": "Quincy Quarries",
      "views": 0,
      "avgTimeSeconds": 0,
      "collectClicks": 0,
      "conversationRate": 0
    },
    {
      "series": "Through the Purple",
      "views": 0,
      "avgTimeSeconds": 0,
      "collectClicks": 0,
      "conversationRate": 0
    },
    {
      "series": "Coastal New England",
      "views": 0,
      "avgTimeSeconds": 0,
      "collectClicks": 0,
      "conversationRate": 0
    },
    {
      "series": "2025 Seasons",
      "views": 0,
      "avgTimeSeconds": 0,
      "collectClicks": 0,
      "conversationRate": 0
    },
    {
      "series": "Portraits",
      "views": 0,
      "avgTimeSeconds": 0,
      "collectClicks": 0,
      "conversationRate": 0
    },
    {
      "series": "The Light Unseen (Infrared Study)",
      "views": 0,
      "avgTimeSeconds": 0,
      "collectClicks": 0,
      "conversationRate": 0
    }
  ],
  "nextBestActions": [
    "Stripe is live — test the full purchase flow end-to-end (browse → select size → Stripe checkout → confirmation)",
    "Begin consistent Instagram posting (3–4 posts/week) to drive first traffic to the site",
    "Verify Plausible tracking survived the Cloudflare migration — check your Plausible dashboard for live visitor data",
    "Share the site link in 2–3 film photography communities (r/analog, Photrio, film photography Discord servers)",
    "First Plausible weekly email arrives next Monday — dashboard data will populate after that"
  ],
  "weeklyTrend": [
    {
      "week": "Mar 31-Apr 6",
      "visitors": 0,
      "collectClicks": 0
    }
  ]
}
